Metadata-Version: 2.1
Name: dbots.py
Version: 1.0.0
Summary: API for dbots.online
Home-page: UNKNOWN
Author: BHBL
License: UNKNOWN
Platform: UNKNOWN
Classifier: Programming Language :: Python :: 3
Classifier: License :: OSI Approved :: MIT License
Classifier: Operating System :: OS Independent
Requires-Python: >=3.6
License-File: LICENSE.txt
